.hgignore
.hgtags
CHANGES.md
COPYING
COPYING.LESSER
MANIFEST.in
README.md
requirements.ipython.txt
requirements.jinja.txt
setup.py
coffeetools/__init__.py
coffeetools.egg-info/PKG-INFO
coffeetools.egg-info/SOURCES.txt
coffeetools.egg-info/dependency_links.txt
coffeetools.egg-info/requires.txt
coffeetools.egg-info/top_level.txt
coffeetools/ipython/__init__.py
coffeetools/jinja/__init__.py