Metadata-Version: 1.1
Name: coffeetools
Version: 0.1.2
Summary: Tools for using CoffeeScript with Python.
Home-page: http://bitbucket.org/userzimmermann/python-coffeetools
Author: Stefan Zimmermann
Author-email: zimmermann.code@gmail.com
License: LGPLv3
Keywords: coffee,tools,script,coffeescript,javascript,jinja,jinja2,jinjatools,template,tag,extension,python3
Platform: UNKNOWN
Classifier: Development Status :: 3 - Alpha
Classifier: Intended Audience :: Developers
Classifier: License :: OSI Approved :: GNU Library or Lesser General Public License (LGPL)
Classifier: Operating System :: OS Independent
Classifier: Programming Language :: Python
Classifier: Programming Language :: Python :: 3
Classifier: Topic :: Software Development
Classifier: Topic :: Utilities
